LICENSE
README.md
SVision.py
setup.cfg
setup.py
SVision.egg-info/PKG-INFO
SVision.egg-info/SOURCES.txt
SVision.egg-info/dependency_links.txt
SVision.egg-info/entry_points.txt
SVision.egg-info/not-zip-safe
SVision.egg-info/requires.txt
SVision.egg-info/top_level.txt
src/__init__.py
src/version.py
src/collection/__init__.py
src/collection/analyze_reads.py
src/collection/classes.py
src/collection/cluster_signatures.py
src/collection/collect_signatures.py
src/collection/graph.py
src/collection/output_clusters.py
src/collection/run_collection.py
src/network/__init__.py
src/network/alexnet.py
src/network/annotation.py
src/network/create_batch.py
src/network/output.py
src/network/predict.py
src/segmentplot/__init__.py
src/segmentplot/classes.py
src/segmentplot/hash_aligner.py
src/segmentplot/plot_segment.py
src/segmentplot/run_hash_lineplot.py