Metadata-Version: 1.2
Name: SVision
Version: 1.3.3
Summary: SV/CSV callers
Home-page: https://github.com/xjtu-omics/SVision
Author: Jiadong Lin, Songbo Wang
Author-email: jiadong66@stu.xjtu.edu.cn, songbowang125@163.com
License: GPLv3
Keywords: SVision,Deep learning,Complex structural variants,Structural variants,Single moleculo sequencing
Platform: UNKNOWN
Classifier: Operating System :: POSIX :: Linux
Classifier: Topic :: Scientific/Engineering :: Bio-Informatics
Classifier: License :: OSI Approved :: GNU General Public License v3 (GPLv3)
Classifier: Programming Language :: Python :: 3.6
Requires-Python: >=3.6
